Browser/__init__.py
Temu_Browser-0.0.0.dist-info/LICENSE.txt
Temu_Browser-0.0.0.dist-info/METADATA
Temu_Browser-0.0.0.dist-info/WHEEL
Temu_Browser-0.0.0.dist-info/top_level.txt
Temu_Browser-0.0.0.dist-info/RECORD
