Metadata-Version: 2.1
Name: Temu-Browser
Version: 0.0.0
Summary: A browsing package
Home-page: https://github.com/pypa/sampleproject1
Author: George Temu
Author-email: georgetemu123@gmail.com
License: UNKNOWN
Platform: UNKNOWN
Classifier: Programming Language :: Python :: 3
Classifier: License :: OSI Approved :: MIT License
Classifier: Operating System :: OS Independent
Requires-Python: >=3.6
